pvqa/__init__.py
pvqa/pipeline/__init__.py
pvqa/pipeline/pvqa_sklearn.py
pvqa/reader/__init__.py
pvqa/reader/bertqa_sklearn.py
pvqa/retriever/__init__.py
pvqa/retriever/retriever_sklearn.py
pvqa/retriever/text_transformers.py
pvqa/retriever/vectorizers.py
pvqa/utils/__init__.py
pvqa/utils/converters.py
pvqa/utils/download.py
pvqa/utils/evaluation.py
pvqa/utils/filters.py
tests/__init__.py
tests/test_converters.py
tests/test_evaluation.py
tests/test_pipeline.py
tests/test_processor.py
pvqa-0.0.2.1.dist-info/METADATA
pvqa-0.0.2.1.dist-info/WHEEL
pvqa-0.0.2.1.dist-info/top_level.txt
pvqa-0.0.2.1.dist-info/RECORD
